unfolded/data_sdk/__init__.py
unfolded/data_sdk/__main__.py
unfolded/data_sdk/_query.py
unfolded/data_sdk/auth.py
unfolded/data_sdk/cli.py
unfolded/data_sdk/data_sdk.py
unfolded/data_sdk/enums.py
unfolded/data_sdk/environment.py
unfolded/data_sdk/errors.py
unfolded/data_sdk/models.py
unfolded/data_sdk/py.typed
unfolded/data_sdk/types.py
unfolded/data_sdk/utils.py
unfolded.data_sdk-0.17.2.dist-info/entry_points.txt
unfolded.data_sdk-0.17.2.dist-info/WHEEL
unfolded.data_sdk-0.17.2.dist-info/METADATA
unfolded.data_sdk-0.17.2.dist-info/RECORD
